setup.cfg
setup.py
serialized_redis/__init__.py
serialized_redis.egg-info/PKG-INFO
serialized_redis.egg-info/SOURCES.txt
serialized_redis.egg-info/dependency_links.txt
serialized_redis.egg-info/requires.txt
serialized_redis.egg-info/top_level.txt