Metadata-Version: 1.0
Name: serialized-redis
Version: 0.1.4
Summary: A solution to have lists and dictionaries serialized using redis-py.
Home-page: http://github.com/EvandroLG/serialized-redis
Author: EvandroLG
Author-email: evandrolgoncalves@gmail.com
License: MIT
Keywords: Redis,redis-py,serialized datas
Platform: UNKNOWN
